[{"fId":"1","fName":"Warung Pecel Mbok Birah","latlng":"-7.850543,111.254339","fWeb":"http://www.example.com","fEmail":"pecelmbokbirah@gmail.com","fOpenToday":"08:00 - 15:00","fPhone":"0273 415 341","fTwitter":"google","fAvaPath":"ava_1.jpg","fImgPath":"pecel_1.jpg","fAdr":"Bangsri, Purwantoro"},
{"fId":"2","fName":"Warung Pecel Yu Painem","latlng":"-7.845207,111.259300","fWeb":"http://www.example.com","fEmail":"yu.painem@gmail.com","fOpenToday":"10:00 - 12:00","fPhone":"0273 415 342","fTwitter":"google","fAvaPath":"ava_2.jpg","fImgPath":"pecel_2.jpg","fAdr":"Ndangkrang, Purwantoro"},
{"fId":"3","fName":"Sego Pecel Super Maknyus","latlng":"-7.85692,111.278286","fWeb":"http://www.example.com","fEmail":"supermak.nyus@gmail.com","fOpenToday":"10:00 - 14:00","fPhone":"0273 415 343","fTwitter":"google","fAvaPath":"ava_3.jpg","fImgPath":"pecel_3.jpg","fAdr":"Tegalrejo, Purwantoro"},
{"fId":"4","fName":"Sego Pecel Tombo Stress","latlng":"-7.835408,111.289186","fWeb":"http://www.example.com","fEmail":"tombo_stress@gmail.com","fOpenToday":"06:00 - 09:00","fPhone":"0273 415 344","fTwitter":"google","fAvaPath":"ava_4.jpg","fImgPath":"pecel_4.jpg","fAdr":"Kepyar, Purwantoro"},
{"fId":"5","fName":"Warung Pecel Pakdhe Tuman","latlng":"-7.837534,111.232538","fWeb":"http://www.example.com","fEmail":"PakdheTuman@gmail.com","fOpenToday":"05:00 - 11:00","fPhone":"0273 415 345","fTwitter":"google","fAvaPath":"ava_5.jpg","fImgPath":"pecel_5.jpg","fAdr":"Joho, Purwantoro"},
{"fId":"6","fName":"Warung Pecel Mas Ucup","latlng":"-7.827245,111.270475","fWeb":"http://www.example.com","fEmail":"Mas.Ucup@gmail.com","fOpenToday":"11:00 - 15:00","fPhone":"0273 415 346","fTwitter":"google","fAvaPath":"ava_6.jpg","fImgPath":"pecel_6.jpg","fAdr":"Gondang, Purwantoro"},
{"fId":"7","fName":"Warung Pecel Barokah","latlng":"-7.832134,111.239018","fWeb":"http://www.example.com","fEmail":"pecelbarokah@gmail.com","fOpenToday":"11:00 - 15:00","fPhone":"0273 415 347","fTwitter":"google","fAvaPath":"ava_7.jpg","fImgPath":"pecel_7.jpg","fAdr":"Miricinde, Purwantoro"},
{"fId":"8","fName":"Nasi Pecel Maimunah","latlng":"-7.86192,111.283586","fWeb":"http://www.example.com","fEmail":"maimunah@gmail.com","fOpenToday":"05:00 - 17:00","fPhone":"0273 415 348","fTwitter":"google","fAvaPath":"ava_8.jpg","fImgPath":"pecel_8.jpg","fAdr":"Tegalrejo, Purwantoro"},
{"fId":"9","fName":"Pecel Muda Mudi","latlng":"-7.831245,111.271075","fWeb":"http://www.example.com","fEmail":"mud4mud1@gmail.com","fOpenToday":"09:00 - 14:00","fPhone":"0273 415 394","fTwitter":"google","fAvaPath":"ava_9.jpg","fImgPath":"pecel_9.jpg","fAdr":"Gondang, Purwantoro"},
{"fId":"10","fName":"Warung Pecel 5758","latlng":"-7.841207,111.259900","fWeb":"http://www.example.com","fEmail":"5758pecel@gmail.com","fOpenToday":"12:00 - 15:00","fPhone":"0273 415 350","fTwitter":"google","fAvaPath":"ava_10.jpg","fImgPath":"pecel_10.jpg","fAdr":"Ndangkrang, Purwantoro"},
{"fId":"11","fName":"Warung Pecel California","latlng":"-7.855543,111.256339","fWeb":"http://www.example.com","fEmail":"calipecel@gmail.com","fOpenToday":"15:00 - 21:00","fPhone":"0273 415 351","fTwitter":"google","fAvaPath":"","fImgPath":"","fAdr":"Bangsri, Purwantoro"}]